mcp_sync/__init__.py
mcp_sync/client_definitions.json
mcp_sync/config.py
mcp_sync/main.py
mcp_sync/sync.py
mcp_sync/clients/__init__.py
mcp_sync/clients/executor.py
mcp_sync/clients/repository.py
mcp_sync/config/__init__.py
mcp_sync/config/models.py
mcp_sync/config/settings.py
mcp_sync-0.4.2.dist-info/METADATA
mcp_sync-0.4.2.dist-info/WHEEL
mcp_sync-0.4.2.dist-info/entry_points.txt
mcp_sync-0.4.2.dist-info/licenses/LICENSE
mcp_sync-0.4.2.dist-info/RECORD
