Metadata-Version: 2.4
Name: mcp-sync
Version: 0.4.2
Summary: Sync MCP (Model Context Protocol) configurations across AI tools
Project-URL: Homepage, https://github.com/ztripez/mcp-sync
Project-URL: Repository, https://github.com/ztripez/mcp-sync
Project-URL: Issues, https://github.com/ztripez/mcp-sync/issues
Project-URL: Documentation, https://github.com/ztripez/mcp-sync#readme
Author-email: ztripez <ztripez@users.noreply.github.com>
License: MIT
License-File: LICENSE
Keywords: ai,configuration,mcp,model-context-protocol,sync
Classifier: Development Status :: 4 - Beta
Classifier: Intended Audience :: Developers
Classifier: License :: OSI Approved :: MIT License
Classifier: Programming Language :: Python :: 3
Classifier: Programming Language :: Python :: 3.12
Classifier: Programming Language :: Python :: 3.13
Classifier: Topic :: Software Development
Classifier: Topic :: System :: Systems Administration
Classifier: Topic :: Utilities
Requires-Python: >=3.12
Requires-Dist: dynaconf>=3.2.11
Requires-Dist: platformdirs>=4.3.8
Requires-Dist: pydantic>=2.11.7
